naver_core/__init__.py
naver_core/datagroup.py
naver_core/middleware.py
naver_core/utils.py
naver_core/dto/__init__.py
naver_core/dto/data.py
naver_core-0.0.3.post8.dist-info/METADATA
naver_core-0.0.3.post8.dist-info/WHEEL
naver_core-0.0.3.post8.dist-info/top_level.txt
naver_core-0.0.3.post8.dist-info/RECORD
