Metadata-Version: 2.1
Name: naver-core
Version: 0.0.3.post8
Summary: A Core Ancestor Library
Home-page: https://github.com/jacr6/naver-core
Author: Jose Cuevas
Author-email: jose.cuevas.cv@gmail.com
License: UNKNOWN
Platform: UNKNOWN
Classifier: Programming Language :: Python :: 3
Classifier: License :: OSI Approved :: MIT License
Classifier: Operating System :: OS Independent
Requires-Dist: naver-config
Requires-Dist: naver-db
Requires-Dist: naver-net
Requires-Dist: naver-web
Requires-Dist: autopep8
Requires-Dist: aniso8601
Requires-Dist: attrs
Requires-Dist: bandit
Requires-Dist: cachetools
Requires-Dist: certifi
Requires-Dist: charset-normalizer
Requires-Dist: click
Requires-Dist: docx
Requires-Dist: docx2pdf
Requires-Dist: docxcompose
Requires-Dist: Flask
Requires-Dist: Flask-Cors
Requires-Dist: flask-restx
Requires-Dist: Flask-SQLAlchemy
Requires-Dist: gitdb
Requires-Dist: GitPython
Requires-Dist: google-api-core
Requires-Dist: google-api-python-client
Requires-Dist: google-auth
Requires-Dist: google-auth-httplib2
Requires-Dist: google-auth-oauthlib
Requires-Dist: googleapis-common-protos
Requires-Dist: greenlet
Requires-Dist: httplib2
Requires-Dist: idna
Requires-Dist: importlib-metadata
Requires-Dist: importlib-resources
Requires-Dist: itsdangerous
Requires-Dist: Jinja2
Requires-Dist: jsonschema
Requires-Dist: lxml
Requires-Dist: MarkupSafe
Requires-Dist: naver-core
Requires-Dist: numpy
Requires-Dist: oauth2client
Requires-Dist: oauthlib
Requires-Dist: openpyxl
Requires-Dist: pandas
Requires-Dist: pathlib
Requires-Dist: pbr
Requires-Dist: Pillow
Requires-Dist: protobuf
Requires-Dist: psycopg2
Requires-Dist: pyasn1
Requires-Dist: pyasn1-modules
Requires-Dist: pyparsing
Requires-Dist: pyrsistent
Requires-Dist: python-consul
Requires-Dist: python-dateutil
Requires-Dist: python-decouple
Requires-Dist: python-docx
Requires-Dist: python-dotenv
Requires-Dist: pytz
Requires-Dist: PyYAML
Requires-Dist: requests
Requires-Dist: requests-oauthlib
Requires-Dist: rsa
Requires-Dist: six
Requires-Dist: smmap
Requires-Dist: SQLAlchemy
Requires-Dist: stevedore
Requires-Dist: tqdm
Requires-Dist: uritemplate
Requires-Dist: urllib3
Requires-Dist: waitress
Requires-Dist: Werkzeug
Requires-Dist: WTForms
Requires-Dist: zipp
